[
    {"id":2,"first_name":"Monica","last_name":"Leone"},
    {"id":3,"first_name":"Eros","last_name":"De Simone"},
    {"id":4,"first_name":"Fabio","last_name":"Vanacore"},
    {"id":5,"first_name":"Federica","last_name":"Federico"},
    {"id":6,"first_name":"Anna","last_name":"Cirillo"},
    {"id":7,"first_name":"Claudia","last_name":"Santonicola"},
    {"id":8,"first_name":"Domenico","last_name":"Vitiello"},
    {"id":9,"first_name":"Federica","last_name":"Marra"},
    {"id":10,"first_name":"Ferdinando","last_name":"D'Auria"},
    {"id":11,"first_name":"Florinda","last_name":"Picari"},
    {"id":12,"first_name":"Giovanni","last_name":"Sicignano"},
    {"id":13,"first_name":"Marika","last_name":"Cangianiello"},
    {"id":14,"first_name":"Martina","last_name":"Tamburro"},
    {"id":15,"first_name":"Pasquale","last_name":"Scutiero"},
    {"id":16,"first_name":"Riccardo","last_name":"Di Bagno"},
    {"id":17,"first_name":"Sabrina","last_name":"Alfano"},
    {"id":18,"first_name":"Sara","last_name":"Carotenuto"},
    {"id":19,"first_name":"Sisto","last_name":"Ametrano"},
    {"id":20,"first_name":"Tania","last_name":"Venditto"},
    {"id":21,"first_name":"Teresa","last_name":"Bozzaotre"}
  ]
  